PyExpPlotting/__init__.py
PyExpPlotting/colors.py
PyExpPlotting/defaults.py
PyExpPlotting/distributions.py
PyExpPlotting/learning_curves.py
PyExpPlotting/matplot.py
PyExpPlotting/py.typed
PyExpPlotting/sensitivity_curves.py
PyExpPlotting/tools.py
PyExpPlotting_andnp-1.0.1.dist-info/WHEEL
PyExpPlotting_andnp-1.0.1.dist-info/METADATA
PyExpPlotting_andnp-1.0.1.dist-info/RECORD
