Metadata-Version: 2.1
Name: PyExpPlotting-andnp
Version: 1.0.1
License: MIT
Author-email: Andy Patterson <andnpatterson@gmail.com>
Requires-Python: >=3.10
Requires-Dist: PyExpUtils-andnp>=3.4.0
Requires-Dist: matplotlib>=2.2.3
Requires-Dist: numba>=0.50.0
Requires-Dist: pandas
Requires-Dist: scipy>=1.5.4
